{
  "description":"H:\\Digitization_Projects\\WWII_Topographic_Maps\\LCMSDS\\GeoTiff-test\\WWIIMMEmden_1945v1_TIFF\\WWIIMMEmden_1945v1_TIFF.tif",
  "driverShortName":"GTiff",
  "driverLongName":"GeoTIFF",
  "files":[
    "H:\\Digitization_Projects\\WWII_Topographic_Maps\\LCMSDS\\GeoTiff-test\\WWIIMMEmden_1945v1_TIFF\\WWIIMMEmden_1945v1_TIFF.tif",
    "H:\\Digitization_Projects\\WWII_Topographic_Maps\\LCMSDS\\GeoTiff-test\\WWIIMMEmden_1945v1_TIFF\\WWIIMMEmden_1945v1_TIFF.tif.ovr",
    "H:\\Digitization_Projects\\WWII_Topographic_Maps\\LCMSDS\\GeoTiff-test\\WWIIMMEmden_1945v1_TIFF\\WWIIMMEmden_1945v1_TIFF.tif.aux.xml"
  ],
  "size":[
    16386,
    11880
  ],
  "coordinateSystem":{
    "wkt":""
  },
  "geoTransform":[
    0.0,
    0.0016666666666667,
    0.0,
    19.8,
    0.0,
    -0.0016666666666667
  ],
  "gcps":{
    "coordinateSystem":{
      "wkt":"PROJCS[\"WGS_1984_Web_Mercator_Auxiliary_Sphere\",\n    GEOGCS[\"GCS_WGS_1984\",\n        DATUM[\"WGS_1984\",\n            SPHEROID[\"WGS_1984\",6378137.0,298.257223563]],\n        PRIMEM[\"Greenwich\",0.0],\n        UNIT[\"Degree\",0.0174532925199433]],\n    PROJECTION[\"Mercator_Auxiliary_Sphere\"],\n    PARAMETER[\"False_Easting\",0.0],\n    PARAMETER[\"False_Northing\",0.0],\n    PARAMETER[\"Central_Meridian\",0.0],\n    PARAMETER[\"Standard_Parallel_1\",0.0],\n    PARAMETER[\"Auxiliary_Sphere_Type\",0.0],\n    UNIT[\"Meter\",1.0],\n    AUTHORITY[\"EPSG\",\"3857\"]]"
    },
    "gcpList":[
      {
        "id":"",
        "info":"",
        "pixel":4160.342417636366008,
        "line":5033.305353677569656,
        "x":803429.734469905379228,
        "y":7048713.15397110208869,
        "z":0.0
      },
      {
        "id":"",
        "info":"",
        "pixel":2460.083212210247439,
        "line":5447.45409398645279,
        "x":800428.956593349110335,
        "y":7048054.714980612508953,
        "z":0.0
      },
      {
        "id":"",
        "info":"",
        "pixel":2526.700814945212187,
        "line":5616.854342853257549,
        "x":800513.214206308592111,
        "y":7047756.625981651246548,
        "z":0.0
      },
      {
        "id":"",
        "info":"",
        "pixel":4805.039928854739628,
        "line":3522.335134531458607,
        "x":804540.044560054317117,
        "y":7051378.542697725817561,
        "z":0.0
      },
      {
        "id":"",
        "info":"",
        "pixel":3465.35479737156902,
        "line":2856.935114968546259,
        "x":802150.280780528206378,
        "y":7052616.879841066896915,
        "z":0.0
      },
      {
        "id":"",
        "info":"",
        "pixel":2733.109193684157617,
        "line":4989.835757717155502,
        "x":800875.021841121837497,
        "y":7048801.501168646849692,
        "z":0.0
      },
      {
        "id":"",
        "info":"",
        "pixel":2404.220211128364099,
        "line":6522.200230742855638,
        "x":800317.834685080568306,
        "y":7046077.478012263774872,
        "z":0.0
      },
      {
        "id":"",
        "info":"",
        "pixel":5831.54315630705878,
        "line":697.533878968424688,
        "x":806370.74087422597222,
        "y":7056547.22020174190402,
        "z":0.0
      }
    ]
  },
  "metadata":{
    "":{
      "TIFFTAG_DATETIME":"2015:04:13 13:52:36",
      "TIFFTAG_RESOLUTIONUNIT":"2 (pixels\/inch)",
      "TIFFTAG_SOFTWARE":"Adobe Photoshop CC 2014 (Windows)",
      "TIFFTAG_XRESOLUTION":"600",
      "TIFFTAG_YRESOLUTION":"600"
    },
    "IMAGE_STRUCTURE":{
      "INTERLEAVE":"PIXEL"
    }
  },
  "cornerCoordinates":{
    "upperLeft":[
      0.0,
      19.8
    ],
    "lowerLeft":[
      0.0,
      0.0
    ],
    "lowerRight":[
      27.31,
      0.0
    ],
    "upperRight":[
      27.31,
      19.8
    ],
    "center":[
      13.655,
      9.9
    ]
  },
  "extent":{
    "type":"Polygon",
    "coordinates":[
      [
      ]
    ]
  },
  "bands":[
    {
      "band":1,
      "block":[
        16386,
        1
      ],
      "type":"Byte",
      "colorInterpretation":"Red",
      "overviews":[
        {
          "size":[
            8193,
            5940
          ]
        },
        {
          "size":[
            4097,
            2970
          ]
        },
        {
          "size":[
            2049,
            1485
          ]
        },
        {
          "size":[
            1025,
            743
          ]
        },
        {
          "size":[
            513,
            372
          ]
        },
        {
          "size":[
            257,
            186
          ]
        }
      ],
      "metadata":{
      }
    },
    {
      "band":2,
      "block":[
        16386,
        1
      ],
      "type":"Byte",
      "colorInterpretation":"Green",
      "overviews":[
        {
          "size":[
            8193,
            5940
          ]
        },
        {
          "size":[
            4097,
            2970
          ]
        },
        {
          "size":[
            2049,
            1485
          ]
        },
        {
          "size":[
            1025,
            743
          ]
        },
        {
          "size":[
            513,
            372
          ]
        },
        {
          "size":[
            257,
            186
          ]
        }
      ],
      "metadata":{
      }
    },
    {
      "band":3,
      "block":[
        16386,
        1
      ],
      "type":"Byte",
      "colorInterpretation":"Blue",
      "overviews":[
        {
          "size":[
            8193,
            5940
          ]
        },
        {
          "size":[
            4097,
            2970
          ]
        },
        {
          "size":[
            2049,
            1485
          ]
        },
        {
          "size":[
            1025,
            743
          ]
        },
        {
          "size":[
            513,
            372
          ]
        },
        {
          "size":[
            257,
            186
          ]
        }
      ],
      "metadata":{
      }
    }
  ]
}